drf_paseto/__init__.py
drf_paseto/authentication.py
drf_paseto-0.1.0.dist-info/LICENSE
drf_paseto-0.1.0.dist-info/METADATA
drf_paseto-0.1.0.dist-info/WHEEL
drf_paseto-0.1.0.dist-info/top_level.txt
drf_paseto-0.1.0.dist-info/RECORD
