Metadata-Version: 2.1
Name: drf-paseto
Version: 0.1.0
Summary: PASETO Authentication for Django REST Framework
Home-page: https://github.com/bahmany/drf_paseto
Author: Mohammad Reza Bahmani
Author-email: bahmanymb@gmail.com
License: UNKNOWN
Platform: UNKNOWN
Classifier: Programming Language :: Python :: 3
Classifier: Framework :: Django
Classifier: License :: OSI Approved :: MIT License
Classifier: Operating System :: OS Independent
Requires-Python: >=3.6
License-File: LICENSE
Requires-Dist: Django (>=3.0)
Requires-Dist: djangorestframework (>=3.11)
Requires-Dist: paseto (>=1.5.2)
